[{
    "Utilities": {
    }
},
{
    "Web Browsers": {
        "Chromium": {
            "program":"chromium-browser"
        },
        "Firefox": {
            "icon":"firefox.png",
            "program":"firefox"
        }
    }
},
{
    "Developer Tools": {
        "Python 3 Development": {
            "program":"python3-devel"
        },
        "OpenJDK Java 7 JDK": {
            "program":"java-1.7.0-openjdk"
        },
        "OpenJDK Java 8 JDK": {
            "program":"java-1.8.0-openjdk"
        }
    }
},
{
    "Graphics": {
    }
},
{
    "Office": {
    }
},
{
    "Media": {
    }
},
{
    "Messaging": {
    }
},
{
    "Gaming": {
        "Steam": {
            "icon":"steam.jpg",
            "program":"steam",
            "warning":"RPM Fusion repositories need to be configured."
        }
    }
},
{
    "Other": {
    }
}]
