[{
    "Utilities": {
        "OpenJDK Java 7 JRE": {
            "icon":"java.jpg"
        },
        "OpenJDK Java 8 JRE": {
            "icon":"java.jpg"
        },
        "Deluge": {
            "icon":"deluge.jpg",
            "program":"deluge"
        },
        "Guake": {
            "icon":"guake.jpg",
            "program":"guake"
        },
        "Shutter": {
            "icon":"shutter.jpg",
            "program":"shutter"
        }
    }
},
{
    "Editors": {
        "Vim": {
            "icon":"vim.jpg",
            "program":"vim"
        },
        "Eclipse": {
            "icon":"eclipse.jpg",
            "program":"eclipse"
        },
        "QTCreator": {
            "icon":"qtcreator.jpg"
        },
        "Geany": {
            "icon":"geany.jpg",
            "program":"geany"
        },
        "Emacs": {
            "icon":"emacs.jpg",
            "program":"emacs"
        }
    }
},
{
    "Web Browsers": {
        "Chromium": {
            "icon":"chromium.jpg"
        },
        "Midori": {
            "icon":"midori.jpg",
            "program":"midori"
        }
    }
},
{
    "Developer Tools": {
        "Python 3 Development": {
            "icon":"python.jpg"
        },
        "OpenJDK Java 7 JDK": {
            "icon":"java.jpg"
        },
        "OpenJDK Java 8 JDK": {
            "icon":"java.jpg"
        },
        "gcc": {
            "icon":"gcc.jpg",
            "program":"gcc"
        },
        "cmake": {
            "icon":"cmake.jpg",
            "program":"cmake"
        },
        "Git": {
            "icon":"git.jpg",
            "program":"git"
        },
        "Svn": {
            "icon":"svn.jpg",
            "program":"svn"
        },
        "Mercurial": {
            "icon":"mercurial.jpg",
            "program":"mercurial"
        }
    }
},
{
    "Graphics": {
        "GIMP": {
            "icon":"gimp.jpg",
            "program":"gimp"
        },
        "Inkscape": {
            "icon":"inkscape.jpg",
            "program":"inkscape"
        },
        "Krita": {
            "icon":"krita.jpg",
            "program":"krita"
        },
        "Blender": {
            "icon":"blender.jpg",
            "program":"blender"
        }
    }
},
{
    "Office": {
        "LibreOffice": {
            "icon":"libreoffice.jpg",
            "program":"libreoffice"
        },
        "OpenOffice": {
            "icon":"openoffice.jpg"
        }
    }
},
{
    "Media": {
        "VLC": {
            "icon":"vlc.jpg",
            "program":"vlc"
        },
        "Audacity": {
            "icon":"audacity.jpg",
            "program":"audacity"
        },
        "Clementine": {
            "icon":"clementine.jpg",
            "program":"clementine"
        },
        "Rhythmbox": {
            "icon":"rhythmbox.jpg",
            "program":"rhythmbox"
        }
    }
},
{
    "Messaging": {
        "Thunderbird": {
            "icon":"thunderbird.jpg",
            "program":"thunderbird"
        },
        "Hexchat": {
            "icon":"hexchat.jpg",
            "program":"hexchat"
        }
    }
},
{
    "Gaming": {
        "Steam": {
            "icon":"steam.jpg",
            "program":"steam"
        }
    }
},
{
    "Other": {
        "Conky": {
            "icon":"conky.jpg",
            "program":"conky"
        },
        "Wine": {
            "icon":"wine.jpg",
            "program":"wine"
        },
        "Zsh": {
            "icon":"zsh.jpg",
            "program":"zsh"
        }
    }
}]
